bossdata/__init__.py
bossdata/bits.py
bossdata/meta.py
bossdata/path.py
bossdata/plate.py
bossdata/plot.py
bossdata/raw.py
bossdata/remote.py
bossdata/spec.py
bossdata-0.3.1.data/scripts/bossfetch
bossdata-0.3.1.data/scripts/bossplot
bossdata-0.3.1.data/scripts/bossquery
bossdata-0.3.1.data/scripts/bossraw
bossdata-0.3.1.data/scripts/bosssky
bossdata-0.3.1.dist-info/DESCRIPTION.rst
bossdata-0.3.1.dist-info/METADATA
bossdata-0.3.1.dist-info/RECORD
bossdata-0.3.1.dist-info/WHEEL
bossdata-0.3.1.dist-info/metadata.json
bossdata-0.3.1.dist-info/top_level.txt
