Metadata-Version: 2.0
Name: bossdata
Version: 0.3.1
Summary: Tools to access SDSS spectroscopic data.
Home-page: https://github.com/dkirkby/bossdata
Author: bossdata developers
Author-email: dkirkby@uci.edu
License: MIT
Keywords: bossdata
Platform: UNKNOWN
Classifier: Development Status :: 4 - Beta
Classifier: Intended Audience :: Science/Research
Classifier: License :: OSI Approved :: MIT License
Classifier: Topic :: Scientific/Engineering :: Astronomy
Classifier: Natural Language :: English
Classifier: Programming Language :: Python :: 2
Classifier: Programming Language :: Python :: 3
Requires-Dist: astropy
Requires-Dist: fitsio
Requires-Dist: numpy
Requires-Dist: progressbar2
Requires-Dist: pydl
Requires-Dist: requests
Requires-Dist: six
